md_ops/__init__.py
md_ops/docx_to_md.py
md_ops/md_to_docx.py
md_ops-1.0.0.dist-info/licenses/LICENSE
md_ops-1.0.0.dist-info/METADATA
md_ops-1.0.0.dist-info/WHEEL
md_ops-1.0.0.dist-info/top_level.txt
md_ops-1.0.0.dist-info/RECORD
