Metadata-Version: 2.4
Name: md-ops
Version: 1.0.0
Summary: Convert Markdown <-> DOCX easily with full formatting support
Home-page: https://github.com/consultanubhav/gpt2docx-be
Author: Consult Anubhav
License: Proprietary
Project-URL: Homepage, https://github.com/consultanubhav/gpt2docx-be
Project-URL: Issues, https://github.com/consultanubhav/gpt2docx-be/issues
Keywords: markdown,docx,converter,word,document
Classifier: Development Status :: 4 - Beta
Classifier: Intended Audience :: Developers
Classifier: Topic :: Software Development :: Libraries :: Python Modules
Classifier: Topic :: Text Processing :: Markup
Classifier: Programming Language :: Python :: 3
Classifier: Programming Language :: Python :: 3.7
Classifier: Programming Language :: Python :: 3.8
Classifier: Programming Language :: Python :: 3.9
Classifier: Programming Language :: Python :: 3.10
Classifier: Programming Language :: Python :: 3.11
Requires-Python: >=3.7
License-File: LICENSE
Requires-Dist: python-docx>=0.8.11
Requires-Dist: markdown2>=2.4.0
Dynamic: home-page
Dynamic: license-file
Dynamic: requires-python
